django_html_xml_validator/__init__.py
django_html_xml_validator/middleware.py
django_html_xml_validator-1.0.0.dist-info/LICENSE
django_html_xml_validator-1.0.0.dist-info/WHEEL
django_html_xml_validator-1.0.0.dist-info/METADATA
django_html_xml_validator-1.0.0.dist-info/RECORD
