Metadata-Version: 2.1
Name: django-html-xml-validator
Version: 1.0.0
Summary: Django middleware to validate HTML and XML responses
Home-page: https://github.com/itell-solutions/django_html_xml_validator
License: MIT
Keywords: django,html,validate,xml
Author: ITELL.SOLUTIONS GmbH
Requires-Python: >=3.7,<4.0
Classifier: Development Status :: 5 - Production/Stable
Classifier: Environment :: Web Environment
Classifier: Framework :: Django
Classifier: Framework :: Django :: 3
Classifier: Framework :: Django :: 4
Classifier: Intended Audience :: Developers
Classifier: License :: OSI Approved :: MIT License
Classifier: Natural Language :: English
Classifier: Operating System :: OS Independent
Classifier: Programming Language :: Python :: 3
Classifier: Programming Language :: Python :: 3 :: Only
Classifier: Programming Language :: Python :: 3.10
Classifier: Programming Language :: Python :: 3.7
Classifier: Programming Language :: Python :: 3.8
Classifier: Programming Language :: Python :: 3.9
Classifier: Topic :: Internet :: WWW/HTTP :: Dynamic Content
Classifier: Topic :: Software Development
Classifier: Topic :: Software Development :: Quality Assurance
Classifier: Topic :: Text Processing :: Markup :: HTML
Classifier: Topic :: Text Processing :: Markup :: XML
Requires-Dist: Django (>=3,<5)
Requires-Dist: lxml (>=4,<5)
Project-URL: Changes, https://github.com/itell-solutions/django_html_xml_validator/blob/main/CHANGES.md
Project-URL: Issue Tracker, https://github.com/itell-solutions/django_html_xml_validator/issues
Project-URL: Repository, https://github.com/itell-solutions/django_html_xml_validator.git
